omnimind/__init__.py
omnimind/client.py
omnimind/config.py
omnimind/utils.py
omnimind-0.1.2.dist-info/LICENSE
omnimind-0.1.2.dist-info/METADATA
omnimind-0.1.2.dist-info/WHEEL
omnimind-0.1.2.dist-info/top_level.txt
omnimind-0.1.2.dist-info/RECORD
