Metadata-Version: 2.1
Name: omnimind
Version: 0.1.2
Summary: A plug-and-play Python library for effortless MCP server integration, powered by Google Gemini
Home-page: https://github.com/Techiral/OmniMind
Author: Lakshya Gupta
Author-email: techiralthefuture@gmail.com
License: MIT
Keywords: open-source,MCP,Model-Context-Protocol,OmniMind,MCP Server,MCP Client,python,AI Agents,AI workflows,AI Automations,AI Tools,Plug & Play,Techiral,Google Gemini
Classifier: Programming Language :: Python :: 3
Classifier: License :: OSI Approved :: MIT License
Classifier: Operating System :: OS Independent
Requires-Python: >=3.6
License-File: LICENSE
